{"authority": "commons-api.metrocuadrado.com", "user-agent": "Mozilla/5.0 (Windows NT 10.0; Win64; x64) AppleWebKit/537.36 (KHTML, like Gecko) Chrome/120.0.0.0 Safari/537.36", "accept": "*/*", "accept-language": "es-419,es;q=0.9,en;q=0.8", "cache-control": "no-cache", "content-type": "application/json", "origin": "https://commons.metrocuadrado.com", "pragma": "no-cache", "sec-ch-ua": "\"Not_A Brand\";v=\"8\", \"Chromium\";v=\"120\", \"Google Chrome\";v=\"120\"", "sec-ch-ua-mobile": "?0", "sec-ch-ua-platform": "\"Windows\"", "sec-fetch-dest": "empty", "sec-fetch-mode": "cors", "sec-fetch-site": "same-site", "x-api-key": "6JgwwXGxlC921DP4SB4ST6Jo6OO7rv3t4yXn5Y8y", "x-audit-client-id": ""}